cellier/__init__.py
cellier/py.typed
cellier/qt_canvas.py
cellier/types.py
cellier/viewer_controller.py
cellier/app/__init__.py
cellier/app/interactivity/__init__.py
cellier/app/interactivity/_labels.py
cellier/app/qt/__init__.py
cellier/app/qt/_orthoview.py
cellier/app/qt/_scene.py
cellier/convenience/__init__.py
cellier/convenience/_viewer_model.py
cellier/convenience/qt/__init__.py
cellier/convenience/qt/qt_viewer.py
cellier/events/__init__.py
cellier/events/_event_bus.py
cellier/events/_mouse.py
cellier/events/_scene.py
cellier/events/_visual.py
cellier/gui/__init__.py
cellier/gui/constants.py
cellier/gui/qt/__init__.py
cellier/gui/qt/utils.py
cellier/models/__init__.py
cellier/models/data_manager.py
cellier/models/viewer.py
cellier/models/data_stores/__init__.py
cellier/models/data_stores/base_data_store.py
cellier/models/data_stores/image.py
cellier/models/data_stores/lines.py
cellier/models/data_stores/points.py
cellier/models/scene/__init__.py
cellier/models/scene/_camera_controller.py
cellier/models/scene/cameras.py
cellier/models/scene/canvas.py
cellier/models/scene/dims_manager.py
cellier/models/scene/scene.py
cellier/models/visuals/__init__.py
cellier/models/visuals/base.py
cellier/models/visuals/image.py
cellier/models/visuals/labels.py
cellier/models/visuals/lines.py
cellier/models/visuals/points.py
cellier/render/__init__.py
cellier/render/_data_classes.py
cellier/render/_render_manager.py
cellier/render/cameras.py
cellier/render/constants.py
cellier/render/image.py
cellier/render/labels.py
cellier/render/lines.py
cellier/render/points.py
cellier/render/utils.py
cellier/render/shaders/__init__.py
cellier/render/shaders/labels.py
cellier/render/shaders/wgsl/__init__.py
cellier/render/shaders/wgsl/label_image.wgsl
cellier/render/shaders/wgsl/volume_ray.wgsl
cellier/slicer/__init__.py
cellier/slicer/slicer.py
cellier/slicer/utils.py
cellier/testing/__init__.py
cellier/testing/_slicing.py
cellier/transform/__init__.py
cellier/transform/_affine.py
cellier-0.0.12.dist-info/METADATA
cellier-0.0.12.dist-info/WHEEL
cellier-0.0.12.dist-info/licenses/LICENSE
cellier-0.0.12.dist-info/RECORD
