Metadata-Version: 2.4
Name: cellier
Version: 0.0.12
Summary: A workshop for rendering cellular models.
Project-URL: homepage, https://github.com/kevinyamauchi/cellier
Project-URL: repository, https://github.com/kevinyamauchi/cellier
Author-email: Kevin Yamauchi <kevin.yamauchi@gmail.com>
License: BSD-3-Clause
License-File: LICENSE
Classifier: Development Status :: 3 - Alpha
Classifier: License :: OSI Approved :: BSD License
Classifier: Programming Language :: Python :: 3
Classifier: Programming Language :: Python :: 3.10
Classifier: Programming Language :: Python :: 3.11
Classifier: Programming Language :: Python :: 3.12
Classifier: Typing :: Typed
Requires-Python: >=3.10
Requires-Dist: cmap>=0.6.0
Requires-Dist: einops>=0.8.1
Requires-Dist: numpy
Requires-Dist: psygnal
Requires-Dist: pydantic
Requires-Dist: pygfx>=0.9.0
Requires-Dist: pylinalg>=0.6.7
Requires-Dist: qtpy
Requires-Dist: scipy>=1.15.2
Requires-Dist: superqt>=0.7.2
Requires-Dist: zarr
Provides-Extra: dev
Requires-Dist: ipython; extra == 'dev'
Requires-Dist: pdbpp; extra == 'dev'
Requires-Dist: pre-commit; extra == 'dev'
Requires-Dist: rich; extra == 'dev'
Requires-Dist: ruff; extra == 'dev'
Provides-Extra: dev-all
Requires-Dist: ipython; extra == 'dev-all'
Requires-Dist: pdbpp; extra == 'dev-all'
Requires-Dist: pre-commit; extra == 'dev-all'
Requires-Dist: pyqt6; extra == 'dev-all'
Requires-Dist: pytest; extra == 'dev-all'
Requires-Dist: pytest-cov; extra == 'dev-all'
Requires-Dist: pytest-qt; extra == 'dev-all'
Requires-Dist: rich; extra == 'dev-all'
Requires-Dist: ruff; extra == 'dev-all'
Requires-Dist: scikit-image; extra == 'dev-all'
Provides-Extra: examples
Requires-Dist: scikit-image; extra == 'examples'
Provides-Extra: pyqt
Requires-Dist: pyqt6; extra == 'pyqt'
Provides-Extra: pyside
Requires-Dist: pyside6; extra == 'pyside'
Provides-Extra: test
Requires-Dist: pytest; extra == 'test'
Requires-Dist: pytest-cov; extra == 'test'
Requires-Dist: pytest-qt; extra == 'test'
